CHANGES.txt
LICENSE.txt
README.txt
bootstrap.py
buildout.cfg
setup.py
src/getpaid/__init__.py
src/getpaid.paypal.egg-info/PKG-INFO
src/getpaid.paypal.egg-info/SOURCES.txt
src/getpaid.paypal.egg-info/dependency_links.txt
src/getpaid.paypal.egg-info/namespace_packages.txt
src/getpaid.paypal.egg-info/not-zip-safe
src/getpaid.paypal.egg-info/requires.txt
src/getpaid.paypal.egg-info/top_level.txt
src/getpaid/paypal/README.txt
src/getpaid/paypal/__init__.py
src/getpaid/paypal/configure.zcml
src/getpaid/paypal/i18n.sh
src/getpaid/paypal/interfaces.py
src/getpaid/paypal/overrides.zcml
src/getpaid/paypal/paypal.py
src/getpaid/paypal/browser/__init__.py
src/getpaid/paypal/browser/getpaidthankyou.py
src/getpaid/paypal/browser/overrides.zcml
src/getpaid/paypal/browser/paypalbutton.py
src/getpaid/paypal/browser/templates/paypalbutton.pt
src/getpaid/paypal/browser/templates/paypalthankyou.pt
src/getpaid/paypal/ipn/__init__.py
src/getpaid/paypal/ipn/configure.zcml
src/getpaid/paypal/ipn/notification.py
src/getpaid/paypal/ipn/submit_handler.py
src/getpaid/paypal/ipn/templates/ipnlistener.pt
src/getpaid/paypal/locales/empty.pt
src/getpaid/paypal/locales/getpaid.paypal.pot
src/getpaid/paypal/locales/manual.pot
src/getpaid/paypal/locales/en/LC_MESSAGES/getpaid.paypal.mo
src/getpaid/paypal/locales/en/LC_MESSAGES/getpaid.paypal.po
src/getpaid/paypal/locales/es/LC_MESSAGES/getpaid.paypal.mo
src/getpaid/paypal/locales/es/LC_MESSAGES/getpaid.paypal.po
src/getpaid/paypal/locales/fi/LC_MESSAGES/getpaid.paypal.mo
src/getpaid/paypal/locales/fi/LC_MESSAGES/getpaid.paypal.po
src/getpaid/paypal/locales/it/LC_MESSAGES/getpaid.paypal.mo
src/getpaid/paypal/locales/it/LC_MESSAGES/getpaid.paypal.po
src/getpaid/paypal/locales/nl/LC_MESSAGE/getpaid.paypal.mo
src/getpaid/paypal/locales/nl/LC_MESSAGE/getpaid.paypal.po